setup.py
shinkenplugins/__init__.py
shinkenplugins.plugins.rabbitmq.egg-info/PKG-INFO
shinkenplugins.plugins.rabbitmq.egg-info/SOURCES.txt
shinkenplugins.plugins.rabbitmq.egg-info/dependency_links.txt
shinkenplugins.plugins.rabbitmq.egg-info/entry_points.txt
shinkenplugins.plugins.rabbitmq.egg-info/namespace_packages.txt
shinkenplugins.plugins.rabbitmq.egg-info/requires.txt
shinkenplugins.plugins.rabbitmq.egg-info/top_level.txt
shinkenplugins/plugins/__init__.py
shinkenplugins/plugins/rabbitmq/__init__.py
shinkenplugins/plugins/rabbitmq/rabbitmq.py