Metadata-Version: 1.0
Name: shinkenplugins.plugins.rabbitmq
Version: 1.0
Summary: Verify good behavior of a RabbitMQ exchange and queue
Home-page: https://github.com/savoirfairelinux/sfl-shinken-plugins
Author: Grégory Starck
Author-email: g.starck@gmail.com
License: GPL3+
Platform: any
